svo_extract/__init__.py
svo_extract-0.0.2.dist-info/LICENSE
svo_extract-0.0.2.dist-info/METADATA
svo_extract-0.0.2.dist-info/WHEEL
svo_extract-0.0.2.dist-info/top_level.txt
svo_extract-0.0.2.dist-info/RECORD
